msffs/__init__.py
msffs/_msffs_impl.py
msffs/_version.py
msffs/api.py
msffs/py.typed
msffs/selector.py
msffs/validation.py
msffs-0.1.0.dist-info/licenses/LICENSE
msffs-0.1.0.dist-info/METADATA
msffs-0.1.0.dist-info/WHEEL
msffs-0.1.0.dist-info/top_level.txt
msffs-0.1.0.dist-info/RECORD
