Metadata-Version: 2.4
Name: msffs
Version: 0.1.0
Summary: mSFFS feature selection with a functional API and sklearn-compatible transformer
License-Expression: MIT
Keywords: feature selection,msffs,scikit-learn
Classifier: Development Status :: 3 - Alpha
Classifier: Intended Audience :: Science/Research
Classifier: Operating System :: OS Independent
Classifier: Programming Language :: Python :: 3
Classifier: Programming Language :: Python :: 3 :: Only
Classifier: Programming Language :: Python :: 3.10
Classifier: Programming Language :: Python :: 3.11
Classifier: Programming Language :: Python :: 3.12
Classifier: Topic :: Scientific/Engineering :: Artificial Intelligence
Requires-Python: >=3.10
License-File: LICENSE
Requires-Dist: numpy>=1.22
Requires-Dist: scikit-learn>=1.2
Provides-Extra: dev
Requires-Dist: pytest>=7.4; extra == "dev"
Requires-Dist: ruff>=0.4; extra == "dev"
Requires-Dist: black>=24.3; extra == "dev"
Requires-Dist: build>=1.2; extra == "dev"
Provides-Extra: test
Requires-Dist: pytest>=7.4; extra == "test"
Dynamic: license-file
